boostml/__init__.py
boostml/preprocessing.py
boostml-0.0.16.dist-info/License.txt
boostml-0.0.16.dist-info/METADATA
boostml-0.0.16.dist-info/WHEEL
boostml-0.0.16.dist-info/top_level.txt
boostml-0.0.16.dist-info/RECORD
