Metadata-Version: 2.1
Name: boostml
Version: 0.0.16
Summary: UNKNOWN
Home-page: UNKNOWN
Author: Ashique Ben
Author-email: ashiquebenjo2112@gmail.com
License: MIT
Platform: UNKNOWN
Classifier: Programming Language :: Python :: 3
Classifier: License :: OSI Approved :: MIT License
Classifier: Operating System :: OS Independent
Requires-Dist: pandas
Requires-Dist: numpy
Requires-Dist: sklearn
